image_processing_devricart/__init__.py
image_processing_devricart/processing/__init__.py
image_processing_devricart/processing/combination.py
image_processing_devricart/processing/transformation.py
image_processing_devricart/utils/__init__.py
image_processing_devricart/utils/io.py
image_processing_devricart/utils/plot.py
image_processing_devricart-0.0.1.dist-info/METADATA
image_processing_devricart-0.0.1.dist-info/WHEEL
image_processing_devricart-0.0.1.dist-info/top_level.txt
image_processing_devricart-0.0.1.dist-info/RECORD
