Metadata-Version: 2.1
Name: image_processing_devricart
Version: 0.0.1
Summary: My short description
Home-page: https://github.com/DevRicart/package-template-DIO
Author: Ricardo Gonçalves
Author-email: ricardo.gferreira97@hotmail.com
Requires-Python: >=3.8
Requires-Dist: matplotlib
Requires-Dist: numpy
Requires-Dist: scikit-image >=0.16.1
